jonstout/actions_demo/__init__.py
jonstout/actions_demo/hello.py
jonstout_actions_demo-0.0.6.dist-info/METADATA
jonstout_actions_demo-0.0.6.dist-info/WHEEL
jonstout_actions_demo-0.0.6.dist-info/top_level.txt
jonstout_actions_demo-0.0.6.dist-info/RECORD
