Metadata-Version: 2.1
Name: jonstout-actions-demo
Version: 0.0.6
Summary: Small example for working with github actions.
Home-page: UNKNOWN
Author: Jonathan Stout
Author-email: jonstout@globalnoc.iu.edu
License: Apache Software License
Platform: UNKNOWN
